<annotation>
	<folder>Dataset</folder>
	<filename>ds42601.jpg</filename>
	<path>C:\Users\sumov\OneDrive\Desktop\Dataset\ds42601.jpg</path>
	<source>
		<database>Unknown</database>
	</source>
	<size>
		<width>1280</width>
		<height>720</height>
		<depth>3</depth>
	</size>
	<segmented>0</segmented>
	<object>
		<name>person</name>
		<pose>Unspecified</pose>
		<truncated>0</truncated>
		<difficult>0</difficult>
		<bndbox>
			<xmin>529</xmin>
			<ymin>357</ymin>
			<xmax>589</xmax>
			<ymax>609</ymax>
		</bndbox>
	</object>
	<object>
		<name>person</name>
		<pose>Unspecified</pose>
		<truncated>0</truncated>
		<difficult>0</difficult>
		<bndbox>
			<xmin>769</xmin>
			<ymin>428</ymin>
			<xmax>834</xmax>
			<ymax>530</ymax>
		</bndbox>
	</object>
	<object>
		<name>person</name>
		<pose>Unspecified</pose>
		<truncated>0</truncated>
		<difficult>0</difficult>
		<bndbox>
			<xmin>409</xmin>
			<ymin>390</ymin>
			<xmax>472</xmax>
			<ymax>533</ymax>
		</bndbox>
	</object>
	<object>
		<name>person</name>
		<pose>Unspecified</pose>
		<truncated>0</truncated>
		<difficult>0</difficult>
		<bndbox>
			<xmin>485</xmin>
			<ymin>390</ymin>
			<xmax>512</xmax>
			<ymax>493</ymax>
		</bndbox>
	</object>
</annotation>
